flask_autoapi/__init__.py
flask_autoapi/command.py
flask_autoapi/endpoint.py
flask_autoapi/model.py
flask_autoapi/form/__init__.py
flask_autoapi/form/field.py
flask_autoapi/form/param.py
flask_autoapi/storage/__init__.py
flask_autoapi/storage/client.py
flask_autoapi/storage/handler.py
flask_autoapi/utils/__init__.py
flask_autoapi/utils/cmd.py
flask_autoapi/utils/diyutils.py
flask_autoapi/utils/filter.py
flask_autoapi/utils/message.py
flask_autoapi/utils/response.py
flask_autoapi-0.12.1.dist-info/METADATA
flask_autoapi-0.12.1.dist-info/WHEEL
flask_autoapi-0.12.1.dist-info/top_level.txt
flask_autoapi-0.12.1.dist-info/zip-safe
flask_autoapi-0.12.1.dist-info/RECORD
