Metadata-Version: 2.1
Name: flask-autoapi
Version: 0.12.1
Summary: 根据模型自动生成 API 接口和文档
Home-page: https://github.com/olivetree123/flask_autoapi
Author: olivetree
Author-email: olivetree123@163.com
License: MIT
Keywords: flask api autoapi
Platform: UNKNOWN
Classifier: License :: OSI Approved :: MIT License
Classifier: Programming Language :: Python
Classifier: Intended Audience :: Developers
Classifier: Operating System :: OS Independent
Requires-Dist: Flask (>=1.1.0)
Requires-Dist: Flask-RESTful (>=0.3.9)
